{
  "$schema": "https://schema.management.azure.com/schemas/2015-01-01/deploymentTemplate.json#",
  "contentVersion": "1.0.0.0",
  "parameters": {
    "virtualNetwork": {
      "defaultValue": {
        "virtualNetworkName": "virtualNetwork"
      },
      "type": "object"
    },
    "nics": {
      "type": "array",
      "defaultValue": [
        {
          "namepreffix": "local",
          "SubnetName": "subnet",
          "privateIPAllocationMethod": "Dynamic",
          "dnsServers": []
        }
      ]
    },
    "StorageType": {
      "type": "string",
      "defaultValue": "Standard_LRS",
      "allowedValues": [
        "Standard_LRS",
        "Standard_ZRS",
        "Standard_GRS",
        "Standard_RAGRS",
        "Premium_LRS"
      ]
    },
    "VMName": {
      "type": "string",
      "minLength": 1,
      "maxLength": 15
    },
    "OSVersion": {
      "type": "string",
      "defaultValue": "2016-Datacenter",
      "allowedValues": [
        "2008-R2-SP1",
        "2012-Datacenter",
        "2012-R2-Datacenter",
        "Windows-Server-Technical-Preview",
        "2016-Datacenter"
      ]
    },
    "AdminUsername": {
      "type": "string",
      "minLength": 1
    },
    "AdminPassword": {
      "type": "securestring"
    }
  },
  "variables": {
    "StorageName": "[concat('storage', uniqueString(resourceGroup().id))]",
    "ImagePublisher": "MicrosoftWindowsServer",
    "ImageOffer": "WindowsServer",
    "OSDiskName": "[concat(parameters('VMName'),'-OSDisk')]",
    "VmSize": "Standard_D2_v2",
    "vNetRef": "[resourceId('Microsoft.Network/virtualNetworks', parameters('virtualNetwork').virtualNetworkName)]",
    "StorageAccountContainerName": "vhds"
  },
  "resources": [
    {
      "name": "[variables('StorageName')]",
      "type": "Microsoft.Storage/storageAccounts",
      "location": "[resourceGroup().location]",
      "apiVersion": "2016-01-01",
      "sku": {
        "name": "[parameters('StorageType')]"
      },
      "dependsOn": [],
      "tags": {
        "displayName": "ProgectNameStorage"
      },
      "kind": "Storage"
    },
    {
      "name": "[concat(parameters('VMName'),'-',parameters('nics')[copyIndex()].namepreffix,'-nic',copyIndex())]",
      "type": "Microsoft.Network/networkInterfaces",
      "location": "[resourceGroup().location]",
      "apiVersion": "2018-02-01",
      "dependsOn": [
        // "[resourceId('Microsoft.Network/virtualNetworks', parameters('virtualNetwork').virtualNetworkName)]"
      ],
      "tags": {},
      "properties": {
        "ipConfigurations": [
          {
            "name": "ipconfig1",
            "properties": {
              "privateIPAllocationMethod": "Dynamic",
              "subnet": {
                "id": "[resourceId('Microsoft.Network/virtualNetworks/subnets', parameters('virtualNetwork').virtualNetworkName, parameters('nics').SubnetName)]"
              }
            }
          }
        ],
        "dnsSettings": {
          "dnsServers": "[parameters('nics')[copyIndex()].dnsServers]"
        }
      },
      "copy": {
        "name": "nics-copy",
        "count": "[length(parameters('nics'))]"
      }
    },
    {
      "name": "[parameters('VMName')]",
      "type": "Microsoft.Compute/virtualMachines",
      "location": "[resourceGroup().location]",
      "apiVersion": "2015-06-15",
      "dependsOn": [
        "[resourceId('Microsoft.Storage/storageAccounts', variables('StorageName'))]",
        "nics-copy"
      ],
      "tags": { },
      "properties": {
        "hardwareProfile": {
          "vmSize": "[variables('VmSize')]"
        },
        "osProfile": {
          "computerName": "[parameters('VMName')]",
          "adminUsername": "[parameters('AdminUsername')]",
          "adminPassword": "[parameters('AdminPassword')]"
        },
        "storageProfile": {
          "imageReference": {
            "publisher": "[variables('ImagePublisher')]",
            "offer": "[variables('ImageOffer')]",
            "sku": "[parameters('OSVersion')]",
            "version": "latest"
          },
          "osDisk": {
            "name": "OSDisk",
            "vhd": {
              "uri": "[concat(reference(resourceId('Microsoft.Storage/storageAccounts', variables('StorageName')), '2016-01-01').primaryEndpoints.blob, variables('StorageAccountContainerName'), '/', variables('OSDiskName'), '.vhd')]"
            },
            "caching": "ReadWrite",
            "createOption": "FromImage"
          },
          "copy": [
            {
              "name": "dataDisks",
              "count": 3,
              "input": {
                "lun": "[copyIndex('dataDisks')]",
                "createOption": "Empty",
                "diskSizeGB": "1023"
              }
            }
          ]
        },
        "networkProfile": {
          "copy": [
            {
              "name": "networkInterfaces",
              "count": "[length(parameters('nics'))]",
              "input": {
                "id": "[resourceId('Microsoft.Network/networkInterfaces', concat(parameters('VMName'),'-',parameters('nics')[copyIndex('networkInterfaces')].namepreffix,'-nic',copyIndex('networkInterfaces')))]"
              }
            }
          ]
        }
      },
      "resources": []
    }
  ],
  "outputs": {
//    "fqdn": {
//      "value": "[reference(parameters('S2SConnectionName')).provisioningState]",
//      "type": "string"
//    },
 //   "ipaddress": {
  //    "value": "[reference(parameters('PublicIPAddressName')).ipAddress]",
  //    "type": "string"
  //  }
  }
}